[
    {
        "jp": "いく",
        "kanji": "行く",
        "tone": 0,
        "pos": "自動Ⅰ",
        "zh": "去"
    },
    {
        "jp": "らいげつ",
        "kanji": "来月",
        "tone": 1,
        "pos": "名",
        "zh": "下个月",
        "romaji": "raigetsu"
    },
    {
        "jp": "バス",
        "kanji": "",
        "tone": 1,
        "pos": "名",
        "zh": "公共汽车,巴士",
        "romaji": "basu"
    },
    {
        "jp": "かえる",
        "kanji": "帰る",
        "tone": 1,
        "pos": "自動Ⅰ",
        "zh": "回家; 青蛙",
        "romaji": "kaeru"
    },
    {
        "jp": "きょねん",
        "kanji": "去年",
        "tone": 1,
        "pos": "名",
        "zh": "去年",
        "romaji": "kyonen"
    },
    {
        "jp": "あに",
        "kanji": "兄",
        "tone": 1,
        "pos": "名",
        "zh": "(我)哥哥",
        "romaji": "ani"
    },
    {
        "jp": "くる",
        "kanji": "来る",
        "tone": 1,
        "pos": "自動Ⅲ",
        "zh": "来",
        "romaji": "kuru"
    },
    {
        "jp": "カレンダー",
        "kanji": "",
        "tone": 2,
        "pos": "名",
        "zh": "日历、挂历"
    },
    {
        "jp": "たんじょうび",
        "kanji": "誕生日",
        "tone": 3,
        "pos": "名",
        "zh": "生日",
        "romaji": "tanjoubi"
    },
    {
        "jp": "かぞく",
        "kanji": "家族",
        "tone": -1,
        "pos": "名",
        "zh": "家庭,家人",
        "score": 3,
        "romaji": "kazoku"
    },
    {
        "jp": "ちち",
        "kanji": "父",
        "tone": 1,
        "pos": "名",
        "zh": "(我)父亲",
        "romaji": "chichi"
    },
    {
        "jp": "はは",
        "kanji": "母",
        "tone": 1,
        "pos": "名",
        "zh": "(我)母亲",
        "romaji": "haha"
    },
    {
        "jp": "あね",
        "kanji": "姉",
        "tone": 0,
        "pos": "名",
        "zh": "(我)姐姐",
        "romaji": "ane"
    },
    {
        "jp": "おとうさん",
        "kanji": "お父さん",
        "tone": 2,
        "pos": "名",
        "zh": "爸爸"
    },
    {
        "jp": "おかあさん",
        "kanji": "お母さん",
        "tone": 2,
        "pos": "名",
        "zh": "妈妈"
    },
    {
        "jp": "おにいさん",
        "kanji": "お兄さん",
        "tone": 2,
        "pos": "名",
        "zh": "哥哥"
    },
    {
        "jp": "おとうとさん",
        "kanji": "弟さん",
        "tone": 0,
        "pos": "名",
        "zh": "弟弟(敬称)"
    },
    {
        "jp": "いもうとさん",
        "kanji": "妹さん",
        "tone": 0,
        "pos": "名",
        "zh": "妹妹(敬称)"
    },
    {
        "jp": "いつ",
        "kanji": "",
        "tone": 1,
        "pos": "疑問",
        "zh": "什么时候",
        "romaji": "itsu"
    },
    {
        "jp": "にゅうがくしき",
        "kanji": "入学式",
        "tone": 4,
        "pos": "名",
        "zh": "入学典礼"
    },
    {
        "jp": "らいねん",
        "kanji": "来年",
        "tone": 0,
        "pos": "名",
        "zh": "明年",
        "romaji": "rainen"
    },
    {
        "jp": "せんげつ",
        "kanji": "先月",
        "tone": 1,
        "pos": "名",
        "zh": "上个月",
        "romaji": "sengetsu"
    },
    {
        "jp": "こんげつ",
        "kanji": "今月",
        "tone": 0,
        "pos": "名",
        "zh": "这个月",
        "romaji": "kongetsu"
    },
    {
        "jp": "まいつき",
        "kanji": "毎月",
        "tone": 0,
        "pos": "名",
        "zh": "每个月"
    },
    {
        "jp": "ことし",
        "kanji": "今年",
        "tone": 0,
        "pos": "名",
        "zh": "今年",
        "romaji": "kotoshi"
    },
    {
        "jp": "まいとし",
        "kanji": "毎年",
        "tone": 0,
        "pos": "名",
        "zh": "每年"
    },
    {
        "jp": "しんかんせん",
        "kanji": "新幹線",
        "tone": 3,
        "pos": "名",
        "zh": "新干线",
        "romaji": "shinkansen"
    },
    {
        "jp": "くるま",
        "kanji": "車",
        "tone": 0,
        "pos": "名",
        "zh": "车; 汽车",
        "romaji": "kuruma"
    },
    {
        "jp": "ひこうき",
        "kanji": "飛行機",
        "tone": 2,
        "pos": "名",
        "zh": "飞机",
        "romaji": "hikouki"
    },
    {
        "jp": "ふね",
        "kanji": "船",
        "tone": 1,
        "pos": "名",
        "zh": "船",
        "romaji": "fune"
    },
    {
        "jp": "じてんしゃ",
        "kanji": "自転車",
        "tone": -1,
        "pos": "名",
        "zh": "自行车",
        "score": 3,
        "romaji": "jitensha"
    },
    {
        "jp": "あるいて",
        "kanji": "歩いて",
        "tone": 2,
        "pos": "副",
        "zh": "步行"
    },
    {
        "jp": "ともだち",
        "kanji": "友だち",
        "tone": 0,
        "pos": "名",
        "zh": "朋友",
        "romaji": "tomodachi"
    },
    {
        "jp": "でんしゃ",
        "kanji": "電車",
        "tone": 0,
        "pos": "名",
        "zh": "电车",
        "romaji": "densha"
    },
    {
        "jp": "いえ",
        "kanji": "家",
        "tone": 2,
        "pos": "名",
        "zh": "家; 房子",
        "romaji": "ie"
    },
    {
        "jp": "ちかてつ",
        "kanji": "地下鉄",
        "tone": 2,
        "pos": "名",
        "zh": "地铁",
        "romaji": "chikatetsu"
    },
    {
        "jp": "タクシー",
        "kanji": "",
        "tone": 1,
        "pos": "名",
        "zh": "出租车",
        "romaji": "takushii"
    },
    {
        "jp": "ひとりで",
        "kanji": "一人で",
        "tone": 2,
        "pos": "副",
        "zh": "一个人"
    },
    {
        "jp": "りょうしん",
        "kanji": "両親",
        "tone": 1,
        "pos": "名",
        "zh": "父母",
        "romaji": "ryoushin"
    },
    {
        "jp": "にっき",
        "kanji": "日記",
        "tone": 0,
        "pos": "名",
        "zh": "日记"
    },
    {
        "jp": "たくさん",
        "kanji": "",
        "tone": 3,
        "pos": "副",
        "zh": "很多"
    }
]