[
    {
        "zh":  "使吃惊",
        "pos":  "adjective",
        "phonetic":  "/.../",
        "score":  5,
        "en":  "astonish"
    },
    {
        "zh":  "旗帜",
        "pos":  "noun",
        "phonetic":  "/.../",
        "score":  5,
        "en":  "banner"
    },
    {
        "zh":  "棒球",
        "pos":  "noun",
        "phonetic":  "/.../",
        "score":  5,
        "en":  "baseball"
    },
    {
        "zh":  "螺栓",
        "pos":  "noun",
        "phonetic":  "/.../",
        "score":  5,
        "en":  "bolt"
    },
    {
        "zh":  "碗",
        "pos":  "noun",
        "phonetic":  "/.../",
        "score":  5,
        "en":  "bowl"
    },
    {
        "zh":  "祝贺",
        "pos":  "noun",
        "phonetic":  "/.../",
        "score":  5,
        "en":  "congratulation"
    },
    {
        "zh":  "连续的",
        "pos":  "adjective",
        "phonetic":  "/.../",
        "score":  5,
        "en":  "consecutive"
    },
    {
        "zh":  "安慰、控制台",
        "pos":  "noun",
        "phonetic":  "/.../",
        "score":  5,
        "en":  "console"
    },
    {
        "zh":  "压碎",
        "pos":  "noun",
        "phonetic":  "/.../",
        "score":  5,
        "en":  "crush"
    },
    {
        "zh":  "聋的",
        "pos":  "adjective",
        "phonetic":  "/.../",
        "score":  5,
        "en":  "deaf"
    },
    {
        "zh":  "恐龙",
        "pos":  "noun",
        "phonetic":  "/.../",
        "score":  5,
        "en":  "dinosaur"
    },
    {
        "zh":  "恐惧",
        "pos":  "noun",
        "phonetic":  "/.../",
        "score":  5,
        "en":  "dread"
    },
    {
        "zh":  "鼓",
        "pos":  "noun",
        "phonetic":  "/.../",
        "score":  5,
        "en":  "drum"
    },
    {
        "zh":  "皇帝",
        "pos":  "noun",
        "phonetic":  "/.../",
        "score":  5,
        "en":  "emperor"
    },
    {
        "zh":  "执行",
        "pos":  "noun",
        "phonetic":  "/.../",
        "score":  5,
        "en":  "execute"
    },
    {
        "zh":  "饥荒",
        "pos":  "noun",
        "phonetic":  "/.../",
        "score":  5,
        "en":  "famine"
    },
    {
        "zh":  "栅栏",
        "pos":  "noun",
        "phonetic":  "/.../",
        "score":  5,
        "en":  "fence"
    },
    {
        "zh":  "火焰",
        "pos":  "noun",
        "phonetic":  "/.../",
        "score":  5,
        "en":  "flame"
    },
    {
        "zh":  "船头",
        "pos":  "noun",
        "phonetic":  "/.../",
        "score":  5,
        "en":  "fore"
    },
    {
        "zh":  "锤",
        "pos":  "noun",
        "phonetic":  "/.../",
        "score":  5,
        "en":  "hammer"
    },
    {
        "zh":  "同类的",
        "pos":  "adjective",
        "phonetic":  "/.../",
        "score":  5,
        "en":  "homogeneous"
    },
    {
        "zh":  "阴谋",
        "pos":  "noun",
        "phonetic":  "/.../",
        "score":  5,
        "en":  "intrigue"
    },
    {
        "zh":  "重叠部分、轻拍、舐",
        "pos":  "noun",
        "phonetic":  "/.../",
        "score":  5,
        "en":  "lap"
    },
    {
        "zh":  "公升",
        "pos":  "noun",
        "phonetic":  "/.../",
        "score":  5,
        "en":  "litre"
    },
    {
        "zh":  "高的、崇高的",
        "pos":  "noun",
        "phonetic":  "/.../",
        "score":  5,
        "en":  "lofty"
    },
    {
        "zh":  "磁铁",
        "pos":  "noun",
        "phonetic":  "/.../",
        "score":  5,
        "en":  "magnet"
    },
    {
        "zh":  "备忘录",
        "pos":  "noun",
        "phonetic":  "/.../",
        "score":  5,
        "en":  "memorandum"
    },
    {
        "zh":  "交往、混合",
        "pos":  "noun",
        "phonetic":  "/.../",
        "score":  5,
        "en":  "mingle"
    },
    {
        "zh":  "小型的、小规模的",
        "pos":  "noun",
        "phonetic":  "/.../",
        "score":  5,
        "en":  "miniature"
    },
    {
        "zh":  "侄女",
        "pos":  "noun",
        "phonetic":  "/.../",
        "score":  5,
        "en":  "niece"
    },
    {
        "zh":  "滋养",
        "pos":  "adjective",
        "phonetic":  "/.../",
        "score":  5,
        "en":  "nourish"
    },
    {
        "zh":  "机构、配备",
        "pos":  "noun",
        "phonetic":  "/.../",
        "score":  5,
        "en":  "outfit"
    },
    {
        "zh":  "熊猫",
        "pos":  "noun",
        "phonetic":  "/.../",
        "score":  5,
        "en":  "panda"
    },
    {
        "zh":  "穿透",
        "pos":  "noun",
        "phonetic":  "/.../",
        "score":  5,
        "en":  "penetrate"
    },
    {
        "zh":  "松树",
        "pos":  "noun",
        "phonetic":  "/.../",
        "score":  5,
        "en":  "pine"
    },
    {
        "zh":  "明信片",
        "pos":  "noun",
        "phonetic":  "/.../",
        "score":  5,
        "en":  "postcard"
    },
    {
        "zh":  "小测验",
        "pos":  "noun",
        "phonetic":  "/.../",
        "score":  5,
        "en":  "quiz"
    },
    {
        "zh":  "破布",
        "pos":  "noun",
        "phonetic":  "/.../",
        "score":  5,
        "en":  "rag"
    },
    {
        "zh":  "叛乱",
        "pos":  "noun",
        "phonetic":  "/.../",
        "score":  5,
        "en":  "rebellion"
    },
    {
        "zh":  "退款",
        "pos":  "noun",
        "phonetic":  "/.../",
        "score":  5,
        "en":  "refund"
    },
    {
        "zh":  "有弹力的",
        "pos":  "adjective",
        "phonetic":  "/.../",
        "score":  5,
        "en":  "resilient"
    },
    {
        "zh":  "咆哮、轰鸣",
        "pos":  "noun",
        "phonetic":  "/.../",
        "score":  5,
        "en":  "roar"
    },
    {
        "zh":  "隔离",
        "pos":  "noun",
        "phonetic":  "/.../",
        "score":  5,
        "en":  "segregate"
    },
    {
        "zh":  "感觉",
        "pos":  "noun",
        "phonetic":  "/.../",
        "score":  5,
        "en":  "sensation"
    },
    {
        "zh":  "袖子",
        "pos":  "noun",
        "phonetic":  "/.../",
        "score":  5,
        "en":  "sleeve"
    },
    {
        "zh":  "细长的、苗条的",
        "pos":  "noun",
        "phonetic":  "/.../",
        "score":  5,
        "en":  "slender"
    },
    {
        "zh":  "滑的",
        "pos":  "adjective",
        "phonetic":  "/.../",
        "score":  5,
        "en":  "slippery"
    },
    {
        "zh":  "袜子",
        "pos":  "noun",
        "phonetic":  "/.../",
        "score":  5,
        "en":  "sock"
    },
    {
        "zh":  "沙发",
        "pos":  "noun",
        "phonetic":  "/.../",
        "score":  5,
        "en":  "sofa"
    },
    {
        "zh":  "西南",
        "pos":  "noun",
        "phonetic":  "/.../",
        "score":  5,
        "en":  "southwest"
    }
]
